biocutils/BooleanList.py
biocutils/Factor.py
biocutils/FloatList.py
biocutils/IntegerList.py
biocutils/NamedList.py
biocutils/Names.py
biocutils/StringList.py
biocutils/__init__.py
biocutils/_utils_combine.py
biocutils/assign.py
biocutils/assign_rows.py
biocutils/assign_sequence.py
biocutils/biocobject.py
biocutils/combine.py
biocutils/combine_columns.py
biocutils/combine_rows.py
biocutils/combine_sequences.py
biocutils/convert_to_dense.py
biocutils/extract_column_names.py
biocutils/extract_row_names.py
biocutils/factorize.py
biocutils/get_height.py
biocutils/intersect.py
biocutils/is_high_dimensional.py
biocutils/is_list_of_type.py
biocutils/is_missing_scalar.py
biocutils/map_to_index.py
biocutils/match.py
biocutils/normalize_subscript.py
biocutils/package_utils.py
biocutils/print_truncated.py
biocutils/print_wrapped_table.py
biocutils/relaxed_combine_columns.py
biocutils/relaxed_combine_rows.py
biocutils/reverse_index.py
biocutils/show_as_cell.py
biocutils/subset.py
biocutils/subset_rows.py
biocutils/subset_sequence.py
biocutils/table.py
biocutils/union.py
biocutils/which.py
biocutils-0.3.4.dist-info/licenses/LICENSE.txt
biocutils-0.3.4.dist-info/METADATA
biocutils-0.3.4.dist-info/WHEEL
biocutils-0.3.4.dist-info/top_level.txt
biocutils-0.3.4.dist-info/RECORD
