Metadata-Version: 2.4
Name: biocutils
Version: 0.3.4
Summary: Utilities to use across the biocpy packages.
Home-page: https://github.com/biocpy/biocutils
Author: Aaron Lun
Author-email: infinite.monkeys.with.keyboards@gmail.com
License: MIT
Project-URL: Documentation, https://github.com/biocpy/biocutils
Platform: any
Classifier: Development Status :: 4 - Beta
Classifier: Programming Language :: Python
Requires-Python: >=3.9
License-File: LICENSE.txt
Requires-Dist: importlib-metadata; python_version < "3.8"
Requires-Dist: numpy
Provides-Extra: testing
Requires-Dist: setuptools; extra == "testing"
Requires-Dist: pytest; extra == "testing"
Requires-Dist: pytest-cov; extra == "testing"
Requires-Dist: pandas; extra == "testing"
Requires-Dist: scipy; extra == "testing"
Dynamic: license-file
